infinity_observability_sdk/__init__.py
infinity_observability_sdk/sdk.py
infinity_observability_sdk-0.1.0.dist-info/METADATA
infinity_observability_sdk-0.1.0.dist-info/WHEEL
infinity_observability_sdk-0.1.0.dist-info/licenses/LICENSE
infinity_observability_sdk-0.1.0.dist-info/RECORD
