Metadata-Version: 2.4
Name: infinity-observability-sdk
Version: 0.1.0
Summary: Infinity Observability SDK
License-File: LICENSE
Requires-Dist: logfire>=4.18.0
Requires-Dist: opentelemetry-exporter-otlp-proto-http>=1.39.1
Requires-Dist: pytest>=9.0.2
Requires-Dist: ruff>=0.14.13
